{
    "characters": [
        {
            "character": {
                "name": "ninja",
                "stats": {
                    "hp": 50,
                    "armor": 5,
                    "magic_resistance": 5,
                    "physical_power": 55,
                    "magic_power": 0,
                    "special_trigger_chance": 15
                }
            }
        },
        {
            "character": {
                "name": "mage",
                "stats": {
                    "hp": 80,
                    "armor": 4,
                    "magic_resistance": 3,
                    "physical_power": 23,
                    "magic_power": 69,
                    "special_trigger_chance": 50
                }
            }
        },
        {
            "character": {
                "name": "mage",
                "stats": {
                    "hp": 87,
                    "armor": 2,
                    "magic_resistance": 3,
                    "physical_power": 21,
                    "magic_power": 56,
                    "special_trigger_chance": 53
                }
            }
        },
        {
            "character": {
                "name": "warrior",
                "stats": {
                    "hp": 288,
                    "armor": 21,
                    "magic_resistance": 47,
                    "physical_power": 27,
                    "magic_power": 2,
                    "special_trigger_chance": 17
                }
            }
        },
        {
            "character": {
                "name": "warrior",
                "stats": {
                    "hp": 274,
                    "armor": 23,
                    "magic_resistance": 46,
                    "physical_power": 30,
                    "magic_power": 0,
                    "special_trigger_chance": 14
                }
            }
        }
    ],
    "items": [
        {
            "name": "shiny_staff",
            "stats": {
                "physical_power": 10,
                "magic_power": 25
            }
        },
        {
            "name": "shiny_staff",
            "stats": {
                "physical_power": 5,
                "magic_power": 34
            }
        },
        {
            "name": "solid_rock",
            "stats": {
                "armor": 22,
                "magic_resistance": 34
            }
        }
    ]
}